docs/__init__.py
docs/source/__init__.py
docs/source/conf.py
pybiographs/__init__.py
pybiographs/covid_data.py
pybiographs/download_data.py
pybiographs/gpickle_to_cytoscape.py
pybiographs/graphs.py
pybiographs/mappings.py
pybiographs/resources.py
pybiographs/version.py
pybiographs/dl_models/__init__.py
pybiographs/dl_models/graph_dl_model.py
pybiographs/dl_models/torch_datasets.py
tests/__init__.py
tests/test_covid_data.py
tests/test_graphs.py
tests/test_mappings.py
pybiographs-0.0.1.dist-info/LICENSE
pybiographs-0.0.1.dist-info/METADATA
pybiographs-0.0.1.dist-info/WHEEL
pybiographs-0.0.1.dist-info/top_level.txt
pybiographs-0.0.1.dist-info/RECORD
